[{"value": "ABBA ABBA CDC DCD", "label": "Petrarchan sonnet"}, {"value": "ABABCBC", "label": "Canopus"}, {"value": "ABCDEF FAEBDC CFDABE ECBFAD DEACFB BDFECA", "label": "Sestina"}, {"value": "AABB", "label": "Clerihew"}, {"value": "ABCB", "label": "Quatrains "}, {"value": "ABAAB", "label": "The Road Not Taken stanza"}, {"value": "ABABB", "label": "Cinquain"}, {"value": "ABCBBB", "label": "The Raven stanza"}, {"value": "ABAB CDCD", "label": "Alternate rhyme"}, {"value": "AAABAB", "label": "Scottish stanza"}, {"value": "ABABBCBCCDCDEE", "label": "Spenserian stanza"}, {"value": "AABA", "label": "Rubaiyat"}, {"value": "ABABBCBC", "label": "Ballade"}, {"value": "AAAAA", "label": "Monorhyme x5"}, {"value": "AA", "label": "Monorhyme x2"}, {"value": "AAA", "label": "Monorhyme x3"}, {"value": "ABABCCDDEDE", "label": "Chant royal"}, {"value": "AA BB", "label": "Couplet x2"}, {"value": "AA BB CC", "label": "Couplet x3"}, {"value": "AA BB CC DD", "label": "Couplet x4"}, {"value": "ABABBCC", "label": "Rhyme royal"}, {"value": "ABAABCBCB", "label": "Fire and Ice stanza"}, {"value": "ABBA", "label": "Enclosed rhyme"}, {"value": "ABABCDECDE", "label": "Keatsian Ode"}, {"value": "ABABCCDDEFFEGG", "label": "Onegin stanzas"}, {"value": "ABAB BCBC CDCD EE", "label": "Spenserian sonnet"}, {"value": "ABAB CDCD EFEF GG", "label": "Shakespearean sonnet"}, {"value": "ABABABCC", "label": "Ottava rima"}, {"value": "BAB CDCD EFEF GG", "label": "Sonnet"}, {"value": "AABBA", "label": "Limerick"}, {"value": "AABCCB", "label": "Boy Named Sue"}, {"value": "AA", "label": "Couplet"}, {"value": "ABA BCB CDC DED", "label": "Terza rima"}, {"value": "AAAA", "label": "Monorhyme x4"}]